llmcachex/__init__.py
llmcachex/async_dedupe.py
llmcachex/cache.py
llmcachex/cli.py
llmcachex/config.py
llmcachex/exceptions.py
llmcachex/hasher.py
llmcachex/models.py
llmcachex/policies.py
llmcachex/replay.py
llmcachex/semantic.py
llmcachex/utils.py
llmcachex-0.2.0.dist-info/licenses/LICENSE
llmcachex-0.2.0.dist-info/METADATA
llmcachex-0.2.0.dist-info/WHEEL
llmcachex-0.2.0.dist-info/entry_points.txt
llmcachex-0.2.0.dist-info/top_level.txt
llmcachex-0.2.0.dist-info/RECORD
