Metadata-Version: 2.4
Name: llmcachex
Version: 0.2.0
Summary: Intelligent caching layer for LLM calls with semantic understanding, async deduplication, and cost control
Author-email: prabhnoor12 <dev@llmcachex.io>
License: MIT
Project-URL: Homepage, https://github.com/prabhnoor12/llmcachex
Project-URL: Documentation, https://github.com/prabhnoor12/llmcachex#readme
Project-URL: Repository, https://github.com/prabhnoor12/llmcachex.git
Project-URL: Issues, https://github.com/prabhnoor12/llmcachex/issues
Keywords: llm,cache,openai,semantic,cost-control,async
Classifier: Development Status :: 4 - Beta
Classifier: Intended Audience :: Developers
Classifier: Topic :: Software Development :: Libraries :: Python Modules
Classifier: License :: OSI Approved :: MIT License
Classifier: Programming Language :: Python :: 3
Classifier: Programming Language :: Python :: 3.9
Classifier: Programming Language :: Python :: 3.10
Classifier: Programming Language :: Python :: 3.11
Classifier: Programming Language :: Python :: 3.12
Classifier: Environment :: Web Environment
Classifier: Operating System :: OS Independent
Requires-Python: >=3.9
License-File: LICENSE
Requires-Dist: openai>=1.3.0
Requires-Dist: fastapi>=0.104.0
Requires-Dist: uvicorn[standard]>=0.24.0
Requires-Dist: click>=8.1.0
Requires-Dist: pydantic>=2.0.0
Requires-Dist: redis>=5.0.0
Requires-Dist: pyyaml>=6.0
Requires-Dist: aiohttp>=3.9.0
Provides-Extra: gateway
Requires-Dist: fastapi>=0.104.0; extra == "gateway"
Requires-Dist: uvicorn[standard]>=0.24.0; extra == "gateway"
Provides-Extra: redis
Requires-Dist: redis>=5.0.0; extra == "redis"
Provides-Extra: dev
Requires-Dist: pytest>=7.4.0; extra == "dev"
Requires-Dist: pytest-asyncio>=0.21.0; extra == "dev"
Requires-Dist: pytest-cov>=4.1.0; extra == "dev"
Requires-Dist: black>=23.0.0; extra == "dev"
Requires-Dist: ruff>=0.1.0; extra == "dev"
Requires-Dist: mypy>=1.5.0; extra == "dev"
Requires-Dist: ipython>=8.15.0; extra == "dev"
Provides-Extra: all
Requires-Dist: llmcachex[dev,gateway,redis]; extra == "all"
Dynamic: license-file
